halo_infinite/__init__.py
halo_infinite/const.py
halo_infinite/csr.py
halo_infinite/game_mode.py
halo_infinite/halo_infinite.py
halo_infinite/match.py
halo_infinite/player.py
halo_infinite-0.0.8.dist-info/LICENSE
halo_infinite-0.0.8.dist-info/METADATA
halo_infinite-0.0.8.dist-info/WHEEL
halo_infinite-0.0.8.dist-info/top_level.txt
halo_infinite-0.0.8.dist-info/RECORD
