Metadata-Version: 2.1
Name: halo-infinite
Version: 0.0.8
Summary: A small package I needed to have on PyPi to make a home assistant integration
Home-page: https://github.com/chadc265/halo-infinite/
License: UNKNOWN
Platform: UNKNOWN
Classifier: Programming Language :: Python :: 3
Classifier: License :: OSI Approved :: MIT License
Classifier: Operating System :: OS Independent
License-File: LICENSE
Requires-Dist: requests (>=2.25.0)
Requires-Dist: furl (>=2.1.0)
